mail_relay/__init__.py
mail_relay/__main__.py
mail_relay/cli/__init__.py
mail_relay/cli/config.py
mail_relay/cli/context.py
mail_relay/cli/info.py
mail_relay/cli/start.py
mail_relay/cli/status.py
mail_relay/cli/stop.py
mail_relay/config/__init__.py
mail_relay/config/config.py
mail_relay/mail/__init__.py
mail_relay/mail/imap.py
mail_relay/mail/smtp.py
mail_relay/secure_channel/__init__.py
mail_relay/secure_channel/base_handler.py
mail_relay/secure_channel/get_keys_handler.py
mail_relay/secure_channel/key_exchange_manager.py
mail_relay/secure_channel/websocket_wrapper.py
mail_relay/store/__init__.py
mail_relay/store/config.py
mail_relay/store/exporter.py
mail_relay/store/handlers.py
mail_relay/store/key.py
mail_relay/store/migrate.py
mail_relay/store/user.py
mail_relay-0.1.1.dist-info/LICENSE
mail_relay-0.1.1.dist-info/METADATA
mail_relay-0.1.1.dist-info/WHEEL
mail_relay-0.1.1.dist-info/entry_points.txt
mail_relay-0.1.1.dist-info/top_level.txt
mail_relay-0.1.1.dist-info/RECORD
