Metadata-Version: 2.1
Name: mail-relay
Version: 0.1.1
Summary: Just a tool to relay incoming emails over to other mail servers
Home-page: https://github.com/samantehrani/mail-relay
Author: Saman Tehrani
Author-email: samanrtehrani@gmail.com
License: MIT
Platform: UNKNOWN
Requires-Python: ==2.7
